coopio/DataAccessExecutor.py
coopio/ICsvDataService.py
coopio/IDataProcessor.py
coopio/IDataService.py
coopio/__init__.py
coopio/sql/SQLDataService.py
coopio/sql/SQLLogging.py
coopio/sql/SqlReturnObj.py
coopio/sql/__init__.py
coopio/sql/dbconnection_args.py
coopio/sql/utils.py
coopio/sql/sqlserver/SQLConnection.py
coopio/sql/sqlserver/SQLQueryExecutor.py
coopio/sql/sqlserver/SQLSpExectutor.py
coopio/sql/sqlserver/__init__.py
tests/__init__.py
tests/dummies.py
tests/test_ICsvDataService.py
tests/test_IDataProcessor.py
tests/test_SQLDataService.py
coopio-1.8.dist-info/LICENSE
coopio-1.8.dist-info/METADATA
coopio-1.8.dist-info/WHEEL
coopio-1.8.dist-info/top_level.txt
coopio-1.8.dist-info/RECORD
