Metadata-Version: 2.1
Name: coopio
Version: 1.8
Summary: Library for creating data services
Home-page: https://github.com/tylertjburns/coopio
Author: tburns
Author-email: tyler.tj.burns@gmail.com
License: MIT
Platform: UNKNOWN
Classifier: Development Status :: 3 - Alpha
Classifier: License :: OSI Approved :: MIT License
Classifier: Programming Language :: Python
Classifier: Programming Language :: Python :: 3.5
Classifier: Programming Language :: Python :: 3.6
Classifier: Topic :: Software Development :: Libraries
Classifier: Topic :: Software Development :: Libraries :: Python Modules
Classifier: Intended Audience :: Developers
Requires-Python: >3.5
License-File: LICENSE
Requires-Dist: atomicwrites (==1.4.0)
Requires-Dist: attrs (==21.2.0)
Requires-Dist: colorama (==0.4.4)
Requires-Dist: cooptools (==0.47)
Requires-Dist: DateTime (==4.3)
Requires-Dist: greenlet (==1.1.0)
Requires-Dist: importlib-metadata (==4.6.1)
Requires-Dist: iniconfig (==1.1.1)
Requires-Dist: nose (==1.3.7)
Requires-Dist: numpy (==1.21.2)
Requires-Dist: object-mapper-coop (==0.0.1)
Requires-Dist: packaging (==21.0)
Requires-Dist: pandas (==1.1.3)
Requires-Dist: pluggy (==0.13.1)
Requires-Dist: py (==1.10.0)
Requires-Dist: pyodbc (==4.0.31)
Requires-Dist: pyparsing (==2.4.7)
Requires-Dist: pytest (==6.2.4)
Requires-Dist: python-dateutil (==2.8.1)
Requires-Dist: pytz (==2020.1)
Requires-Dist: six (==1.15.0)
Requires-Dist: SQLAlchemy (==1.4.22)
Requires-Dist: SQLAlchemy-Utils (==0.37.8)
Requires-Dist: toml (==0.10.2)
Requires-Dist: typing-extensions (==3.10.0.0)
Requires-Dist: zipp (==3.5.0)
Requires-Dist: zope.interface (==5.4.0)
